pydantic_typeddict.py
pydantic_typeddict-0.1.0.dist-info/WHEEL
pydantic_typeddict-0.1.0.dist-info/METADATA
pydantic_typeddict-0.1.0.dist-info/RECORD
