Metadata-Version: 2.1
Name: pydantic-typeddict
Version: 0.1.0
Summary: 
License: MIT
Author: asduj
Author-email: asduj@ya.ru
Requires-Python: >=3.8,<4.0
Classifier: License :: OSI Approved :: MIT License
Classifier: Programming Language :: Python :: 3
Classifier: Programming Language :: Python :: 3.8
Requires-Dist: pydantic (>=1.4,<2.0)
